llm_toolbridge/__init__.py
llm_toolbridge/adapters/__init__.py
llm_toolbridge/adapters/azure_openai.py
llm_toolbridge/adapters/gemini.py
llm_toolbridge/adapters/openai.py
llm_toolbridge/core/__init__.py
llm_toolbridge/core/adapter.py
llm_toolbridge/core/adapter_registry.py
llm_toolbridge/core/bridge.py
llm_toolbridge/core/config.py
llm_toolbridge/core/provider.py
llm_toolbridge/core/schema.py
llm_toolbridge/core/tool.py
llm_toolbridge/providers/__init__.py
llm_toolbridge/providers/azure_openai.py
llm_toolbridge/providers/gemini.py
llm_toolbridge/providers/openai.py
llm_toolbridge/utils/__init__.py
llm_toolbridge/utils/env_loader.py
llm_toolbridge-0.1.0.dist-info/METADATA
llm_toolbridge-0.1.0.dist-info/WHEEL
llm_toolbridge-0.1.0.dist-info/top_level.txt
llm_toolbridge-0.1.0.dist-info/RECORD
